{
  "errors": [
    "./index.js\nModule build failed: SyntaxError: 'import' and 'export' may only appear at the top level (44:2)\n\n\u001b[0m \u001b[90m 42 | \u001b[39m  module\u001b[33m.\u001b[39mexports \u001b[33m=\u001b[39m _ReactDatum\n \u001b[90m 43 | \u001b[39m} \u001b[36melse\u001b[39m{\n\u001b[31m\u001b[1m>\u001b[22m\u001b[39m\u001b[90m 44 | \u001b[39m  \u001b[36mexport\u001b[39m \u001b[36mconst\u001b[39m {\n \u001b[90m    | \u001b[39m  \u001b[31m\u001b[1m^\u001b[22m\u001b[39m\n \u001b[90m 45 | \u001b[39m    \n \u001b[90m 46 | \u001b[39m    \u001b[90m// Contextual components\u001b[39m\n \u001b[90m 47 | \u001b[39m    \u001b[33mClickToEditForm\u001b[39m\u001b[33m,\u001b[39m   \u001b[0m\n\nBabelLoaderError: SyntaxError: 'import' and 'export' may only appear at the top level (44:2)\n\n\u001b[0m \u001b[90m 42 | \u001b[39m  module\u001b[33m.\u001b[39mexports \u001b[33m=\u001b[39m _ReactDatum\n \u001b[90m 43 | \u001b[39m} \u001b[36melse\u001b[39m{\n\u001b[31m\u001b[1m>\u001b[22m\u001b[39m\u001b[90m 44 | \u001b[39m  \u001b[36mexport\u001b[39m \u001b[36mconst\u001b[39m {\n \u001b[90m    | \u001b[39m  \u001b[31m\u001b[1m^\u001b[22m\u001b[39m\n \u001b[90m 45 | \u001b[39m    \n \u001b[90m 46 | \u001b[39m    \u001b[90m// Contextual components\u001b[39m\n \u001b[90m 47 | \u001b[39m    \u001b[33mClickToEditForm\u001b[39m\u001b[33m,\u001b[39m   \u001b[0m\n\n    at transpile (/Users/bwilkerson/projects/zulily/react-datum/node_modules/babel-loader/lib/index.js:64:13)\n    at Object.module.exports (/Users/bwilkerson/projects/zulily/react-datum/node_modules/babel-loader/lib/index.js:171:20)\n @ multi ././index.js"
  ],
  "warnings": [],
  "version": "3.4.1",
  "hash": "032148af8299024aa91c",
  "publicPath": "dist/",
  "assetsByChunkName": {
    "main": "react-datum.js"
  },
  "assets": [
    {
      "name": "react-datum.js",
      "size": 3662,
      "chunks": [
        0
      ],
      "chunkNames": [
        "main"
      ]
    }
  ],
  "entrypoints": {
    "main": {
      "chunks": [
        0
      ],
      "assets": [
        "react-datum.js"
      ]
    }
  },
  "chunks": [
    {
      "id": 0,
      "rendered": true,
      "initial": true,
      "entry": true,
      "extraAsync": false,
      "size": 717,
      "names": [
        "main"
      ],
      "files": [
        "react-datum.js"
      ],
      "hash": "76538b3409ab6cbcaa07",
      "parents": [],
      "modules": [
        {
          "id": 0,
          "identifier": "multi ././index.js",
          "name": "multi ././index.js",
          "index": 0,
          "index2": 1,
          "size": 28,
          "cacheable": true,
          "built": true,
          "optional": false,
          "prefetched": false,
          "chunks": [
            0
          ],
          "assets": [],
          "issuer": null,
          "issuerId": null,
          "issuerName": null,
          "failed": false,
          "errors": 0,
          "warnings": 0,
          "reasons": [],
          "usedExports": true,
          "providedExports": null,
          "optimizationBailout": [],
          "depth": 0
        },
        {
          "id": 1,
          "identifier": "/Users/bwilkerson/projects/zulily/react-datum/node_modules/cache-loader/dist/cjs.js!/Users/bwilkerson/projects/zulily/react-datum/node_modules/babel-loader/lib/index.js!/Users/bwilkerson/projects/zulily/react-datum/index.js",
          "name": "./index.js",
          "index": 1,
          "index2": 0,
          "size": 689,
          "cacheable": true,
          "built": true,
          "optional": false,
          "prefetched": false,
          "chunks": [
            0
          ],
          "assets": [],
          "issuer": "multi ././index.js",
          "issuerId": 0,
          "issuerName": "multi ././index.js",
          "failed": true,
          "errors": 1,
          "warnings": 0,
          "reasons": [
            {
              "moduleId": 0,
              "moduleIdentifier": "multi ././index.js",
              "module": "multi ././index.js",
              "moduleName": "multi ././index.js",
              "type": "single entry",
              "userRequest": "././index.js",
              "loc": "main:100000"
            }
          ],
          "usedExports": true,
          "providedExports": null,
          "optimizationBailout": [],
          "depth": 1,
          "source": "throw new Error(\"Module build failed: SyntaxError: 'import' and 'export' may only appear at the top level (44:2)\\n\\n\\u001b[0m \\u001b[90m 42 | \\u001b[39m  module\\u001b[33m.\\u001b[39mexports \\u001b[33m=\\u001b[39m _ReactDatum\\n \\u001b[90m 43 | \\u001b[39m} \\u001b[36melse\\u001b[39m{\\n\\u001b[31m\\u001b[1m>\\u001b[22m\\u001b[39m\\u001b[90m 44 | \\u001b[39m  \\u001b[36mexport\\u001b[39m \\u001b[36mconst\\u001b[39m {\\n \\u001b[90m    | \\u001b[39m  \\u001b[31m\\u001b[1m^\\u001b[22m\\u001b[39m\\n \\u001b[90m 45 | \\u001b[39m    \\n \\u001b[90m 46 | \\u001b[39m    \\u001b[90m// Contextual components\\u001b[39m\\n \\u001b[90m 47 | \\u001b[39m    \\u001b[33mClickToEditForm\\u001b[39m\\u001b[33m,\\u001b[39m   \\u001b[0m\\n\");"
        }
      ],
      "filteredModules": 0,
      "origins": [
        {
          "moduleId": 0,
          "module": "multi ././index.js",
          "moduleIdentifier": "multi ././index.js",
          "moduleName": "multi ././index.js",
          "loc": "",
          "name": "main",
          "reasons": []
        }
      ]
    }
  ],
  "modules": [
    {
      "id": 0,
      "identifier": "multi ././index.js",
      "name": "multi ././index.js",
      "index": 0,
      "index2": 1,
      "size": 28,
      "cacheable": true,
      "built": true,
      "optional": false,
      "prefetched": false,
      "chunks": [
        0
      ],
      "assets": [],
      "issuer": null,
      "issuerId": null,
      "issuerName": null,
      "failed": false,
      "errors": 0,
      "warnings": 0,
      "reasons": [],
      "usedExports": true,
      "providedExports": null,
      "optimizationBailout": [],
      "depth": 0
    },
    {
      "id": 1,
      "identifier": "/Users/bwilkerson/projects/zulily/react-datum/node_modules/cache-loader/dist/cjs.js!/Users/bwilkerson/projects/zulily/react-datum/node_modules/babel-loader/lib/index.js!/Users/bwilkerson/projects/zulily/react-datum/index.js",
      "name": "./index.js",
      "index": 1,
      "index2": 0,
      "size": 689,
      "cacheable": true,
      "built": true,
      "optional": false,
      "prefetched": false,
      "chunks": [
        0
      ],
      "assets": [],
      "issuer": "multi ././index.js",
      "issuerId": 0,
      "issuerName": "multi ././index.js",
      "failed": true,
      "errors": 1,
      "warnings": 0,
      "reasons": [
        {
          "moduleId": 0,
          "moduleIdentifier": "multi ././index.js",
          "module": "multi ././index.js",
          "moduleName": "multi ././index.js",
          "type": "single entry",
          "userRequest": "././index.js",
          "loc": "main:100000"
        }
      ],
      "usedExports": true,
      "providedExports": null,
      "optimizationBailout": [],
      "depth": 1,
      "source": "throw new Error(\"Module build failed: SyntaxError: 'import' and 'export' may only appear at the top level (44:2)\\n\\n\\u001b[0m \\u001b[90m 42 | \\u001b[39m  module\\u001b[33m.\\u001b[39mexports \\u001b[33m=\\u001b[39m _ReactDatum\\n \\u001b[90m 43 | \\u001b[39m} \\u001b[36melse\\u001b[39m{\\n\\u001b[31m\\u001b[1m>\\u001b[22m\\u001b[39m\\u001b[90m 44 | \\u001b[39m  \\u001b[36mexport\\u001b[39m \\u001b[36mconst\\u001b[39m {\\n \\u001b[90m    | \\u001b[39m  \\u001b[31m\\u001b[1m^\\u001b[22m\\u001b[39m\\n \\u001b[90m 45 | \\u001b[39m    \\n \\u001b[90m 46 | \\u001b[39m    \\u001b[90m// Contextual components\\u001b[39m\\n \\u001b[90m 47 | \\u001b[39m    \\u001b[33mClickToEditForm\\u001b[39m\\u001b[33m,\\u001b[39m   \\u001b[0m\\n\");"
    }
  ],
  "filteredModules": 0,
  "children": []
}